vec2graph/__init__.py
vec2graph/genviz.html
vec2graph/genviz.js
vec2graph/genviz.py
vec2graph/data/genviz.html
vec2graph/data/genviz.js
vec2graph-0.3.0.dist-info/METADATA
vec2graph-0.3.0.dist-info/RECORD
vec2graph-0.3.0.dist-info/WHEEL
vec2graph-0.3.0.dist-info/top_level.txt
